markdownmaker/__init__.py
markdownmaker/document.py
markdownmaker/markdownmaker.py
markdownmaker-0.4.0.dist-info/LICENSE.md
markdownmaker-0.4.0.dist-info/METADATA
markdownmaker-0.4.0.dist-info/WHEEL
markdownmaker-0.4.0.dist-info/top_level.txt
markdownmaker-0.4.0.dist-info/RECORD
