Metadata-Version: 2.1
Name: markdownmaker
Version: 0.4.0
Summary: An easy-to-use Python to Markdown generator.
Home-page: https://gitlab.com/MoritzBrueckner/markdownmaker
Author: Moritz Brückner
License: zlib
Project-URL: Documentation, https://gitlab.com/MoritzBrueckner/markdownmaker
Project-URL: Source, https://gitlab.com/MoritzBrueckner/markdownmaker
Project-URL: Tracker, https://gitlab.com/MoritzBrueckner/markdownmaker/-/issues
Keywords: markdownmaker Markdown Syntax Layout Library Utility Generator Converter Tool
Platform: UNKNOWN
Classifier: Development Status :: 4 - Beta
Classifier: Intended Audience :: End Users/Desktop
Classifier: Intended Audience :: Developers
Classifier: License :: OSI Approved :: zlib/libpng License
Classifier: Operating System :: POSIX :: Linux
Classifier: Programming Language :: Python :: 3 :: Only
Classifier: Programming Language :: Python :: 3.6
Classifier: Programming Language :: Python :: 3.7
Classifier: Programming Language :: Python :: 3.8
Classifier: Programming Language :: Python :: 3.9
Classifier: Topic :: Text Processing
Classifier: Topic :: Text Processing :: Markup
Classifier: Topic :: Text Processing :: Markup :: Markdown
Classifier: Topic :: Utilities
Classifier: Typing :: Typed
Requires-Python: >=3.6
